<?xml version="1.0" encoding="utf-8"?>
<prefix name="mochigames" label="Mochi Games" language_tag="ru-RU" language_label="Russia"><key name="added"/><key name="additional_settings_title"/><key name="add_btn_label"/><key name="add_category"/><key name="add_to_favourites_btn_label"/><key name="admin_configuration_required_notification"/><key name="admin_links_settings_heading"/><key name="auth_action_label_add_comment"/><key name="auth_action_label_play_games"/><key name="auth_group_label"/><key name="by"/><key name="category_1"/><key name="category_10"/><key name="category_11"/><key name="category_12"/><key name="category_13"/><key name="category_14"/><key name="category_15"/><key name="category_16"/><key name="category_17"/><key name="category_18"/><key name="category_2"/><key name="category_3"/><key name="category_4"/><key name="category_5"/><key name="category_6"/><key name="category_7"/><key name="category_8"/><key name="category_9"/><key name="category_added"/><key name="category_deleted"/><key name="category_desc"/><key name="category_field_label"/><key name="category_label"/><key name="category_list_label"/><key name="cmp_widget_background_color"/><key name="cmp_widget_defaultTab"/><key name="cmp_widget_height"/><key name="cmp_widget_show_position_label"/><key name="cmp_widget_slug"/><key name="cmp_widget_width"/><key name="coins_revshare_enabled"/><key name="coming_soon"/><key name="comments_widget_title"/><key name="comment_activity_string"/><key name="credits_for_play_game"/><key name="demo_btn_label"/><key name="desc_swf_warning"/><key name="error_add"/><key name="error_game_exists"/><key name="featured_list_page_description"/><key name="featured_list_page_heading"/><key name="field_description"/><key name="field_embed_code"/><key name="field_game_tag"/><key name="field_is_enabled"/><key name="field_is_featured"/><key name="field_name"/><key name="field_swf"/><key name="field_thumbnail"/><key name="form_add_game_item"/><key name="game_desc_added"/><key name="game_desc_coins"/><key name="game_desc_content_rating"/><key name="game_desc_control_scheme"/><key name="game_desc_created_by"/><key name="game_desc_description"/><key name="game_desc_instructions"/><key name="game_desc_primary_category"/><key name="game_desc_secondary_category"/><key name="game_desc_size"/><key name="game_desc_slug"/><key name="game_desc_tag"/><key name="game_desc_tags"/><key name="game_edit_form_error_message"/><key name="game_list"/><key name="game_page_heading"/><key name="game_widget_title"/><key name="highscores"/><key name="invitation_join_string"/><key name="invite_btn_label"/><key name="invite_friends_widget_title"/><key name="item_deleted"/><key name="latest_list_page_description"/><key name="latest_list_page_heading"/><key name="leaderboard_widget_title"/><key name="like_activity_string"/><key name="limit_per_page_settings"/><key name="list_page_heading"/><key name="list_settings_title"/><key name="main_menu_item"/><key name="menu_item_add_custom_game"/><key name="menu_item_add_game"/><key name="menu_item_categories"/><key name="menu_item_configuration_settings"/><key name="menu_item_manage_games"/><key name="new_game_item"/><key name="no"/><key name="now_playing"/><key name="no_items"/><key name="no_players"/><key name="play_activity_string"/><key name="position_label_bronze"/><key name="position_label_gold"/><key name="position_label_silver"/><key name="post_on_site_btn_label"/><key name="post_on_site_info"/><key name="publisher_id_settings"/><key name="publisher_secret_key_settings"/><key name="publisher_settings_saved"/><key name="recommendation_level_settings"/><key name="results_by_category"/><key name="results_by_name"/><key name="results_by_tag"/><key name="saved"/><key name="save_btn_label"/><key name="score_activity_string"/><key name="score_results"/><key name="score_widget_title"/><key name="search_by_category"/><key name="search_by_tag"/><key name="search_by_title"/><key name="search_list_page_description"/><key name="search_list_page_heading"/><key name="tags_field_label"/><key name="top-rated_list_page_description"/><key name="top-rated_list_page_heading"/><key name="total_games"/><key name="total_score_label"/><key name="usercredits_action_get_highscore"/><key name="usercredits_action_play_game"/><key name="users_invite_success_message"/><key name="verification_code_settings"/><key name="widgets_panel_heading"/><key name="yes"/></prefix>
