<?xml version="1.0" encoding="utf-8"?>
<prefix name="slideshow" label="Image Slideshow" language_tag="ru-RU" language_label="Russia"><key name="add_image"><value>Добавить изображение</value></key><key name="add_new"><value>Добавить новый</value></key><key name="add_slide"><value>Добавить слайд</value></key><key name="confirm_delete_plugin"><value>Вы уверены, что хотите удалить этот плагин?</value></key><key name="delete_content"><value>Удалить содержимое и удалить плагин</value></key><key name="delete_content_desc"><value>Перед установкой плагина слайд-шоу, мы должны удалить все существующие слайд-шоу. Это может занять некоторое время.</value></key><key name="delete_content_warning"><value>Внимание</value></key><key name="delete_slide_confirm"><value>Вы уверены, что хотите удалить слайд?</value></key><key name="edit_slide"><value>Изменить слайд</value></key><key name="effect"><value>Эффект</value></key><key name="effect_fade"><value>fade</value></key><key name="effect_slide"><value>слайд</value></key><key name="file"><value>Файл</value></key><key name="images"><value>Изображения</value></key><key name="interval"><value>Интервал</value></key><key name="interval_long"><value>длинный</value></key><key name="interval_medium"><value>положение</value></key><key name="interval_short"><value>short</value></key><key name="label"><value>Этикетка</value></key><key name="navigation"><value>Навигация</value></key><key name="no_images"><value>Изображения не добавлены</value></key><key name="optional"><value>Опции</value></key><key name="page_title_uninstall"><value>Удалить слайд-шоу плагин</value></key><key name="plugin_set_for_uninstall"><value>Слайд-шоу плагин удален.</value></key><key name="rearrange_tip"><value>Используйте &lt;span class="ow_mild_green"&gt;Drag'n'drop&lt;/span&gt;, чтобы изменить порядок изображений.</value></key><key name="settings"><value>Настройки слайд-шоу</value></key><key name="uninstall_inprogress"><value>В процессе</value></key><key name="uninstall_inprogress_desc"><value>Пожалуйста подождите, пока все слайд-шоу будут удалены. Это может занять некоторое время в зависимости от количества слайд-шоу на вашем сайте.</value></key><key name="unprogress"/><key name="unprogress_desc"/><key name="url"><value>URL</value></key><key name="widget_title"><value>Слайд-шоу</value></key></prefix>
