<?xml version="1.0" encoding="utf-8"?>
<prefix name="user_status" label="Status Updates" language_tag="ru-RU" language_label="Russia"><key name="activity_string"><value>&lt;a href="{$actorUrl}"&gt;{$actor}&lt;/a&gt; {$status}</value></key><key name="edit_status_widget_title"><value>Что происходит?</value></key><key name="foo"><value>&lt;</value></key><key name="profile_page_heading"><value>{$username} &lt;span class="ow_small"&gt;{$status}&lt;/span&gt;</value></key><key name="send"><value>Отправить</value></key><key name="updated"><value>Обновлённый статус показан в activity steam</value></key></prefix>
